{"nodes": [{"id": "c_xampp_htdocs_gorozpev2_vetsys_app_models_coggin_php", "label": "Coggin.php", "file_type": "code", "source_file": "app/Models/Coggin.php", "source_location": "L1"}, {"id": "c_xampp_htdocs_gorozpev2_vetsys_app_models_coggin_coggin", "label": "Coggin", "file_type": "code", "source_file": "app/Models/Coggin.php", "source_location": "L8", "_callable": true}, {"id": "model", "label": "Model", "file_type": "code", "source_file": "", "source_location": ""}, {"id": "hasfactory", "label": "HasFactory", "file_type": "code", "source_file": "", "source_location": ""}, {"id": "c_xampp_htdocs_gorozpev2_vetsys_app_models_coggin_coggin_tenant", "label": ".tenant()", "file_type": "code", "source_file": "app/Models/Coggin.php", "source_location": "L19", "_callable": true}, {"id": "c_xampp_htdocs_gorozpev2_vetsys_app_models_coggin_coggin_club", "label": ".club()", "file_type": "code", "source_file": "app/Models/Coggin.php", "source_location": "L24", "_callable": true}], "edges": [{"source": "c_xampp_htdocs_gorozpev2_vetsys_app_models_coggin_php", "target": "hasfactory", "relation": "imports", "context": "import", "confidence": "EXTRACTED", "source_file": "app/Models/Coggin.php", "source_location": "L5", "weight": 1.0}, {"source": "c_xampp_htdocs_gorozpev2_vetsys_app_models_coggin_php", "target": "model", "relation": "imports", "context": "import", "confidence": "EXTRACTED", "source_file": "app/Models/Coggin.php", "source_location": "L6", "weight": 1.0}, {"source": "c_xampp_htdocs_gorozpev2_vetsys_app_models_coggin_php", "target": "c_xampp_htdocs_gorozpev2_vetsys_app_models_coggin_coggin", "relation": "contains", "confidence": "EXTRACTED", "source_file": "app/Models/Coggin.php", "source_location": "L8", "weight": 1.0}, {"source": "c_xampp_htdocs_gorozpev2_vetsys_app_models_coggin_coggin", "target": "model", "relation": "inherits", "confidence": "EXTRACTED", "source_file": "app/Models/Coggin.php", "source_location": "L8", "weight": 1.0}, {"source": "c_xampp_htdocs_gorozpev2_vetsys_app_models_coggin_coggin", "target": "hasfactory", "relation": "mixes_in", "confidence": "EXTRACTED", "source_file": "app/Models/Coggin.php", "source_location": "L10", "weight": 1.0}, {"source": "c_xampp_htdocs_gorozpev2_vetsys_app_models_coggin_coggin", "target": "c_xampp_htdocs_gorozpev2_vetsys_app_models_coggin_coggin_tenant", "relation": "method", "confidence": "EXTRACTED", "source_file": "app/Models/Coggin.php", "source_location": "L19", "weight": 1.0}, {"source": "c_xampp_htdocs_gorozpev2_vetsys_app_models_coggin_coggin", "target": "c_xampp_htdocs_gorozpev2_vetsys_app_models_coggin_coggin_club", "relation": "method", "confidence": "EXTRACTED", "source_file": "app/Models/Coggin.php", "source_location": "L24", "weight": 1.0}], "raw_calls": [{"caller_nid": "c_xampp_htdocs_gorozpev2_vetsys_app_models_coggin_coggin_tenant", "callee": "belongsTo", "is_member_call": true, "source_file": "app/Models/Coggin.php", "source_location": "L21", "receiver": null}, {"caller_nid": "c_xampp_htdocs_gorozpev2_vetsys_app_models_coggin_coggin_club", "callee": "belongsTo", "is_member_call": true, "source_file": "app/Models/Coggin.php", "source_location": "L26", "receiver": null}]}